{
	"setting": {
		"urlCheck": false,
		"es6": true,
		"enhance": true,
		"postcss": true,
		"preloadBackgroundData": false,
		"minified": true,
		"newFeature": true,
		"coverView": true,
		"nodeModules": true,
		"autoAudits": true,
		"showShadowRootInWxmlPanel": true,
		"scopeDataCheck": true,
		"uglifyFileName": true,
		"checkInvalidKey": true,
		"checkSiteMap": true,
		"uploadWithSourceMap": true,
		"babelSetting": {
			"ignore": [],
			"disablePlugins": [],
			"outputPath": ""
		},
		"bundle": true
	},
	"compileType": "miniprogram",
	"libVersion": "2.9.4",
	"appid": "wx9877fbefcd53ad3e",
	"projectname": "%E9%97%A8%E6%88%B7",
	"isGameTourist": false,
	"simulatorType": "wechat",
	"simulatorPluginLibVersion": {},
	"condition": {}
}